pyrodigal_gv/__init__.py
pyrodigal_gv/__main__.py
pyrodigal_gv/cli.py
pyrodigal_gv/meta.json
pyrodigal_gv/meta.py
pyrodigal_gv/py.typed
pyrodigal_gv/tests/__init__.py
pyrodigal_gv/tests/phage_Agate.faa
pyrodigal_gv/tests/phage_Agate.fna
pyrodigal_gv/tests/phage_Agate.scores.txt
pyrodigal_gv/tests/phage_Topaz.faa
pyrodigal_gv/tests/phage_Topaz.fna
pyrodigal_gv/tests/phage_Topaz.scores.txt
pyrodigal_gv/tests/requirements.txt
pyrodigal_gv/tests/test_gene_finder.py
pyrodigal_gv-0.3.1.dist-info/COPYING
pyrodigal_gv-0.3.1.dist-info/METADATA
pyrodigal_gv-0.3.1.dist-info/WHEEL
pyrodigal_gv-0.3.1.dist-info/entry_points.txt
pyrodigal_gv-0.3.1.dist-info/top_level.txt
pyrodigal_gv-0.3.1.dist-info/RECORD
