Metadata-Version: 2.1
Name: pyrodigal-gv
Version: 0.3.1
Summary: A Pyrodigal extension to predict genes in giant viruses and viruses with alternative genetic code.
Home-page: https://github.com/althonos/pyrodigal-gv
Author: Martin Larralde
Author-email: martin.larralde@embl.de
License: GPLv3
Project-URL: Bug Tracker, https://github.com/althonos/pyrodigal-gv/issues
Project-URL: Changelog, https://github.com/althonos/pyrodigal-gv/blob/master/CHANGELOG.md
Project-URL: Coverage, https://codecov.io/gh/althonos/pyrodigal-gv/
Project-URL: Builds, https://github.com/althonos/pyrodigal-gv/actions
Project-URL: PyPI, https://pypi.org/project/pyrodigal-gv
Keywords: bioinformatics,genome,orf,gene,prodigal
Platform: any
Classifier: Development Status :: 4 - Beta
Classifier: Intended Audience :: Developers
Classifier: Intended Audience :: Science/Research
Classifier: License :: OSI Approved :: GNU General Public License v3 (GPLv3)
Classifier: Operating System :: OS Independent
Classifier: Programming Language :: Python :: 3.6
Classifier: Programming Language :: Python :: 3.7
Classifier: Programming Language :: Python :: 3.8
Classifier: Programming Language :: Python :: 3.9
Classifier: Programming Language :: Python :: 3.10
Classifier: Programming Language :: Python :: 3.11
Classifier: Programming Language :: Python :: 3.12
Classifier: Programming Language :: Python :: Implementation :: CPython
Classifier: Programming Language :: Python :: Implementation :: PyPy
Classifier: Topic :: Scientific/Engineering :: Bio-Informatics
Classifier: Topic :: Scientific/Engineering :: Medical Science Apps.
Classifier: Typing :: Typed
Requires-Python: >=3.6
License-File: COPYING
Requires-Dist: pyrodigal !=3.2.0,~=3.2
Requires-Dist: importlib-resources ; python_version < "3.9"
